csuffixtree-0.3.6.dist-info/METADATA
csuffixtree-0.3.6.dist-info/RECORD
csuffixtree-0.3.6.dist-info/WHEEL
csuffixtree-0.3.6.dist-info/top_level.txt
suffixtree/RegularExpSearch.py
suffixtree/SimpleStringSearch.py
suffixtree/SuffixForest.py
suffixtree/SuffixTree.py
suffixtree/SuffixTreePyBinding.dll
suffixtree/TestClass.py
suffixtree/__init__.py
suffixtree/libSuffixTreePyBinding.so
