Metadata-Version: 2.1
Name: csuffixtree
Version: 0.3.6
Summary: A C implemented Suffix Tree package
Home-page: https://github.com/oneengineer/suffixtree
Author: oneengineer
Author-email: oneengineer@gmail.com
License: UNKNOWN
Platform: UNKNOWN
Requires-Dist: automaton-tools
